libreria_G5/__init__.py
libreria_G5/libreriaG5.py
libreria_G5-0.1.3.dist-info/LICENSE
libreria_G5-0.1.3.dist-info/METADATA
libreria_G5-0.1.3.dist-info/WHEEL
libreria_G5-0.1.3.dist-info/top_level.txt
libreria_G5-0.1.3.dist-info/RECORD
