Metadata-Version: 2.1
Name: libreria-G5
Version: 0.1.3
Summary: This library contains different functions to facilitate data preprocessing.
Author: Group 5: Garazi Alba, Janire Fuentes, Marcos Garro, Julen Olabarria, Mikel Ortega, Ekhi Sarasa
Author-email: garazi.alba@alumni.mondragon.edu
Classifier: Programming Language :: Python :: 3
Classifier: License :: OSI Approved :: MIT License
Classifier: Operating System :: OS Independent
Requires-Python: >=3.6
License-File: LICENSE
Requires-Dist: pandas (>=1.0.0)
Requires-Dist: numpy (>=1.18.0)
Requires-Dist: scikit-learn (>=0.24.0)
Requires-Dist: matplotlib (>=3.3.0)
Requires-Dist: seaborn (>=0.11.0)
